pptx2mdplus/__init__.py
pptx2mdplus/__main__.py
pptx2mdplus/entry.py
pptx2mdplus/image.py
pptx2mdplus/log.py
pptx2mdplus/multi_column.py
pptx2mdplus/outputter.py
pptx2mdplus/parser.py
pptx2mdplus/types.py
pptx2mdplus/utils.py
pptx2md_plus-2.1.1.dist-info/LICENSE
pptx2md_plus-2.1.1.dist-info/METADATA
pptx2md_plus-2.1.1.dist-info/WHEEL
pptx2md_plus-2.1.1.dist-info/entry_points.txt
pptx2md_plus-2.1.1.dist-info/RECORD
